circle/__init__.py
circle/web3/__init__.py
circle/web3/user_controlled_wallets/__init__.py
circle/web3/user_controlled_wallets/api_client.py
circle/web3/user_controlled_wallets/api_response.py
circle/web3/user_controlled_wallets/configuration.py
circle/web3/user_controlled_wallets/exceptions.py
circle/web3/user_controlled_wallets/py.typed
circle/web3/user_controlled_wallets/rest.py
circle/web3/user_controlled_wallets/api/__init__.py
circle/web3/user_controlled_wallets/api/pin_authentication_api.py
circle/web3/user_controlled_wallets/api/signing_api.py
circle/web3/user_controlled_wallets/api/social_email_authentication_api.py
circle/web3/user_controlled_wallets/api/token_lookup_api.py
circle/web3/user_controlled_wallets/api/transactions_api.py
circle/web3/user_controlled_wallets/api/users_api.py
circle/web3/user_controlled_wallets/api/wallets_api.py
circle/web3/user_controlled_wallets/models/__init__.py
circle/web3/user_controlled_wallets/models/abi_parameters_inner.py
circle/web3/user_controlled_wallets/models/accelerate_transaction_for_end_user_request.py
circle/web3/user_controlled_wallets/models/accelerate_transaction_for_end_user_response.py
circle/web3/user_controlled_wallets/models/account_type.py
circle/web3/user_controlled_wallets/models/bad_request_response.py
circle/web3/user_controlled_wallets/models/balance.py
circle/web3/user_controlled_wallets/models/balances.py
circle/web3/user_controlled_wallets/models/balances_data.py
circle/web3/user_controlled_wallets/models/base_screening_decision.py
circle/web3/user_controlled_wallets/models/blockchain.py
circle/web3/user_controlled_wallets/models/cancel_transaction_for_end_user_request.py
circle/web3/user_controlled_wallets/models/cancel_transaction_for_end_user_response.py
circle/web3/user_controlled_wallets/models/challenge.py
circle/web3/user_controlled_wallets/models/challenge_response.py
circle/web3/user_controlled_wallets/models/challenge_response_data.py
circle_user_controlled_wallets-9.1.0.dist-info/METADATA
circle_user_controlled_wallets-9.1.0.dist-info/WHEEL
circle_user_controlled_wallets-9.1.0.dist-info/top_level.txt
circle_user_controlled_wallets-9.1.0.dist-info/RECORD
